pytiktok/__init__.py
pytiktok/tiktok.py
pytiktok-1.1.1.dist-info/LICENSE
pytiktok-1.1.1.dist-info/METADATA
pytiktok-1.1.1.dist-info/WHEEL
pytiktok-1.1.1.dist-info/top_level.txt
pytiktok-1.1.1.dist-info/RECORD
