Metadata-Version: 2.1
Name: pytiktok
Version: 1.1.1
Summary: A small example package
Home-page: https://github.com/muntazir-halim/pytiktok
Author: ruks
Author-email: ameer800040008000@gmail.com
License: UNKNOWN
Project-URL: Bug Tracker, https://github.com/pypa/sampleproject/issues
Platform: UNKNOWN
Classifier: Programming Language :: Python :: 3
Classifier: License :: OSI Approved :: MIT License
Classifier: Operating System :: OS Independent
Requires-Python: >=3.6
License-File: LICENSE
